auto_config-0.4.0.dist-info/METADATA
auto_config-0.4.0.dist-info/WHEEL
auto_config-0.4.0.dist-info/entry_points.txt
auto_config/__init__.py
auto_config/__main__.py
auto_config/__version__.py
auto_config/device.py
auto_config/field.py
auto_config/generator/__init__.py
auto_config/generator/ansible_hosts.py
auto_config/generator/base.py
auto_config/generator/caddy_file.py
auto_config/generator/dns_hosts.py
auto_config/generator/dns_manager.py
auto_config/generator/ssh_hosts.py
auto_config/service.py
auto_config/utils.py
auto_config-0.4.0.dist-info/RECORD
