Metadata-Version: 2.1
Name: auto-config
Version: 0.4.0
Summary: auto config for my personal devices
Author-Email: Zhan Rongrui <2742392377@qq.com>
License: MIT
Classifier: Environment :: Console
Classifier: Operating System :: OS Independent
Classifier: License :: OSI Approved :: GNU General Public License v3 (GPLv3)
Classifier: Typing :: Typed
Classifier: Programming Language :: Python
Classifier: Programming Language :: Python :: 3
Classifier: Programming Language :: Python :: 3.10
Classifier: Programming Language :: Python :: 3.11
Classifier: Programming Language :: Python :: 3.12
Classifier: Programming Language :: Python :: 3.13
Classifier: Programming Language :: Python :: Implementation :: CPython
Project-URL: Homepage, https://pypi.org/project/auto-config
Project-URL: Repository, https://github.com/zrr1999/auto-config.git
Requires-Python: >=3.10
Requires-Dist: pydantic>=2.5.3
Requires-Dist: typer>=0.16.0
Requires-Dist: loguru>=0.7.3
Requires-Dist: toml>=0.10.2
